{
    "$schema": "https://laravel-ide.com/schema/laravel-ide-v2.json",
    "completions": [
        {
            "complete": "directoryFiles",
            "options": {
                "directory": "resources/views/messages",
                "suffixToClear": ".blade.php"
            },
            "condition": [
                {
                    "functionNames": [
                        "message"
                    ],
                    "parameters": [
                        1
                    ]
                }
            ]
        },
        {
            "complete": "staticStrings",
            "options": {
                "strings": [
                    "bot-core"
                ]
            },
            "condition": [
                {
                    "functionNames": [
                        "message"
                    ],
                    "parameters": [
                        3
                    ]
                }
            ]
        }
    ]
}
